[
    {
      "id": "amangalik",
      "password": "Mitski",
      "cart": [
        {
            "id": 1,
            "name": "Bar Soap",
            "stock": 2,
            "description": "Lorem ipsum dolor sit amet, consectetur adipiscing elit.",
            "tags": ["Organic", "Unscented", "Hygiene"]
        },
        {
            "id": 2,
            "name": "Liquid Soap",
            "stock": 4,
            "description": "Nulla blandit nulla sit amet fringilla accumsan.",
            "tags": ["Organic", "Unscented", "Hygiene"]
        },
        {
            "id": 3,
            "name": "Shampoo",
            "stock": 6,
            "description": "Phasellus porttitor erat nec enim sagittis tristique.",
            "tags": ["Organic", "Unscented", "Hair Care"]
          },
          {
            "id": 4,
            "name": "Conditioner",
            "stock": 8,
            "description": "Aliquam tempor nisl a scelerisque fringilla.",
            "tags": ["Organic", "Unscented", "Hair Care"]
          }
      ]
    }
]